setup.py
base64_util/__init__.py
base64_util.egg-info/PKG-INFO
base64_util.egg-info/SOURCES.txt
base64_util.egg-info/dependency_links.txt
base64_util.egg-info/not-zip-safe
base64_util.egg-info/top_level.txt